stimkit/__init__.py
stimkit/canvas.py
stimkit/io.py
stimkit/layouts.py
stimkit/render.py
stimkit/collections/__init__.py
stimkit/collections/lines.py
stimkit/collections/notched_circle.py
stimkit/collections/shapes.py
stimkit/resources/NotoSansSC-Regular.ttf
stimkit/resources/__init__.py
stimkit-0.2.0.dist-info/METADATA
stimkit-0.2.0.dist-info/WHEEL
stimkit-0.2.0.dist-info/licenses/LICENSE
stimkit-0.2.0.dist-info/RECORD
