Metadata-Version: 2.4
Name: stimkit
Version: 0.2.0
Summary: Canvas, renderer, and layout utilities for the Stim project.
License-File: LICENSE
Requires-Python: >=3.12
Requires-Dist: h5py>=3.15.1
Requires-Dist: loguru>=0.7.3
Requires-Dist: matplotlib>=3.10.8
Requires-Dist: numpy>=2.3.5
Requires-Dist: openpyxl>=3.1.5
Requires-Dist: pandas>=2.3.3
Requires-Dist: polars>=1.36.1
Requires-Dist: pyarrow>=22.0.0
Requires-Dist: pydantic>=2.12.5
Requires-Dist: python-docx>=1.1.2
Requires-Dist: scipy>=1.16.3
Requires-Dist: tqdm>=4.67.1
Requires-Dist: typer>=0.20.1
